marisa_trie.cp35-win_amd64.pyd
marisa_trie_m-0.7.6.dist-info/AUTHORS.rst
marisa_trie_m-0.7.6.dist-info/LICENSE
marisa_trie_m-0.7.6.dist-info/METADATA
marisa_trie_m-0.7.6.dist-info/WHEEL
marisa_trie_m-0.7.6.dist-info/top_level.txt
marisa_trie_m-0.7.6.dist-info/RECORD
